./1527_process.log
./PKG-INFO
./README.md
./genie_room.py
./language.json
./mcp_server.py
./model_serving_utils.py
./package_name
./pyproject.toml
./requirements.txt
./token_minter.py
./.vscode/settings.json
iflow_mcp_vivian_xie_db_genie_mcp_server-0.1.0.dist-info/METADATA
iflow_mcp_vivian_xie_db_genie_mcp_server-0.1.0.dist-info/WHEEL
iflow_mcp_vivian_xie_db_genie_mcp_server-0.1.0.dist-info/entry_points.txt
iflow_mcp_vivian_xie_db_genie_mcp_server-0.1.0.dist-info/RECORD
