Metadata-Version: 2.4
Name: iflow-mcp_vivian-xie-db-genie_mcp_server
Version: 0.1.0
Summary: Genie MCP Server - A server for interacting with Databricks Genie via MCP StreamableHTTP Protocol
Requires-Python: >=3.8
Requires-Dist: backoff>=2.2.0
Requires-Dist: databricks-sdk>=0.20.0
Requires-Dist: httpx>=0.24.0
Requires-Dist: mcp>=0.9.0
Requires-Dist: pandas>=2.0.0
Requires-Dist: python-dotenv>=1.0.0
Requires-Dist: requests>=2.31.0
Requires-Dist: starlette>=0.27.0
Requires-Dist: uvicorn>=0.23.0
